{
  "gitSyncId": "682d4d2a92cca105dbc17693_6362fa5a-4dd8-4a6f-9151-62a08d743c4e",
  "id": "Kế hoạch - Báo cáo_QueryBCNotInKH",
  "pluginId": "postgres-plugin",
  "pluginType": "DB",
  "unpublishedAction": {
    "actionConfiguration": {
      "body": "SELECT \n  bc.*\nFROM bao_cao bc\nWHERE bc.id NOT IN (\n  SELECT DISTINCT bao_cao_id FROM ke_hoach_bao_cao\n)\nAND 1=1\n  {{ SelectNamBCNotInKH.selectedOptionValue ? `AND EXTRACT(YEAR FROM bc.ngay_ban_hanh) = ${SelectNamBCNotInKH.selectedOptionValue}` : \"\" }}\n  {{ SelectQuyBCNotInKH.selectedOptionValue ? `\n      AND CEIL(EXTRACT(MONTH FROM bc.ngay_ban_hanh)::numeric / 3) = ${SelectQuyBCNotInKH.selectedOptionValue}` : \"\" }}\n  {{ SelectThangBCNotInKH.selectedOptionValue ? `AND EXTRACT(MONTH FROM bc.ngay_ban_hanh) = ${SelectThangBCNotInKH.selectedOptionValue}` : \"\" }};\n",
      "encodeParamsToggle": true,
      "paginationType": "NONE",
      "pluginSpecifiedTemplates": [
        {
          "value": false
        }
      ],
      "timeoutInMillisecond": 10000
    },
    "confirmBeforeExecute": false,
    "datasource": {
      "id": "csdltc",
      "isAutoGenerated": false,
      "name": "csdltc",
      "pluginId": "postgres-plugin"
    },
    "dynamicBindingPathList": [
      {
        "key": "body"
      }
    ],
    "executeOnLoad": true,
    "name": "QueryBCNotInKH",
    "pageId": "Kế hoạch - Báo cáo",
    "userSetOnLoad": true
  }
}