{
  "animateLoading": true,
  "backgroundColor": "#FFFFFF",
  "borderColor": "#E0DEDE",
  "borderRadius": "{{appsmith.theme.borderRadius.appBorderRadius}}",
  "borderWidth": "1",
  "bottomRow": 198,
  "boxShadow": "{{appsmith.theme.boxShadow.appBoxShadow}}",
  "children": [
    {
      "borderRadius": "{{appsmith.theme.borderRadius.appBorderRadius}}",
      "bottomRow": 450,
      "boxShadow": "{{appsmith.theme.boxShadow.appBoxShadow}}",
      "canExtend": false,
      "containerStyle": "none",
      "detachFromLayout": true,
      "dynamicBindingPathList": [
        {
          "key": "borderRadius"
        },
        {
          "key": "boxShadow"
        }
      ],
      "dynamicHeight": "AUTO_HEIGHT",
      "flexLayers": [],
      "isLoading": false,
      "isVisible": true,
      "key": "fpb5utuor1",
      "leftColumn": 0,
      "maxDynamicHeight": 9000,
      "minDynamicHeight": 4,
      "minHeight": 100,
      "minWidth": 450,
      "mobileBottomRow": 100,
      "mobileLeftColumn": 0,
      "mobileRightColumn": 451.28515625,
      "mobileTopRow": 0,
      "needsErrorInfo": false,
      "parentColumnSpace": 1,
      "parentId": "y63mkjbtup",
      "parentRowSpace": 1,
      "renderMode": "CANVAS",
      "responsiveBehavior": "fill",
      "rightColumn": 451.28515625,
      "topRow": 0,
      "type": "CANVAS_WIDGET",
      "version": 1,
      "widgetId": "9my5qzzd58",
      "widgetName": "Canvas124"
    }
  ],
  "containerStyle": "card",
  "dynamicBindingPathList": [
    {
      "key": "borderRadius"
    },
    {
      "key": "boxShadow"
    }
  ],
  "dynamicHeight": "AUTO_HEIGHT",
  "flexVerticalAlignment": "stretch",
  "isCanvas": true,
  "isLoading": false,
  "isVisible": true,
  "key": "e45hnm5c9q",
  "leftColumn": 0,
  "maxDynamicHeight": 9000,
  "minDynamicHeight": 10,
  "minWidth": 450,
  "mobileBottomRow": 66,
  "mobileLeftColumn": 0,
  "mobileRightColumn": 23,
  "mobileTopRow": 56,
  "needsErrorInfo": false,
  "originalBottomRow": 265,
  "originalTopRow": 153,
  "parentColumnSpace": 19.62109375,
  "parentId": "r05dfkqjoa",
  "parentRowSpace": 10,
  "renderMode": "CANVAS",
  "responsiveBehavior": "fill",
  "rightColumn": 64,
  "shouldScrollContents": true,
  "topRow": 153,
  "type": "CONTAINER_WIDGET",
  "version": 1,
  "widgetId": "y63mkjbtup",
  "widgetName": "Container5"
}