{
  "accentColor": "#553de9",
  "animateLoading": true,
  "backgroundColor": "#FFFFFF",
  "borderColor": "#E0DEDE",
  "borderRadius": "{{appsmith.theme.borderRadius.appBorderRadius}}",
  "borderWidth": 1,
  "bottomRow": 109,
  "boxShadow": "{{appsmith.theme.boxShadow.appBoxShadow}}",
  "children": [
    {
      "borderRadius": "{{appsmith.theme.borderRadius.appBorderRadius}}",
      "bottomRow": 1010,
      "boxShadow": "{{appsmith.theme.boxShadow.appBoxShadow}}",
      "canExtend": true,
      "detachFromLayout": true,
      "dynamicBindingPathList": [
        {
          "key": "borderRadius"
        },
        {
          "key": "boxShadow"
        }
      ],
      "dynamicHeight": "AUTO_HEIGHT",
      "dynamicTriggerPathList": [],
      "flexLayers": [],
      "isDisabled": false,
      "isLoading": false,
      "isVisible": true,
      "key": "d1i677ai0n",
      "leftColumn": 0,
      "maxDynamicHeight": 9000,
      "minDynamicHeight": 4,
      "minHeight": 150,
      "minWidth": 450,
      "mobileBottomRow": 150,
      "mobileLeftColumn": 0,
      "mobileRightColumn": 587.25,
      "mobileTopRow": 0,
      "needsErrorInfo": false,
      "parentColumnSpace": 1,
      "parentId": "jd6m2w0g0x",
      "parentRowSpace": 1,
      "renderMode": "CANVAS",
      "responsiveBehavior": "fill",
      "rightColumn": 587.25,
      "shouldScrollContents": false,
      "tabId": "tab1",
      "tabName": "I3",
      "topRow": 0,
      "type": "CANVAS_WIDGET",
      "version": 1,
      "widgetId": "lsw27ydv9u",
      "widgetName": "Canvas136"
    },
    {
      "borderRadius": "{{appsmith.theme.borderRadius.appBorderRadius}}",
      "bottomRow": 1010,
      "boxShadow": "{{appsmith.theme.boxShadow.appBoxShadow}}",
      "canExtend": true,
      "detachFromLayout": true,
      "dynamicBindingPathList": [
        {
          "key": "borderRadius"
        },
        {
          "key": "boxShadow"
        }
      ],
      "dynamicHeight": "AUTO_HEIGHT",
      "dynamicTriggerPathList": [],
      "flexLayers": [],
      "isDisabled": false,
      "isLoading": false,
      "isVisible": true,
      "key": "d1i677ai0n",
      "leftColumn": 0,
      "maxDynamicHeight": 9000,
      "minDynamicHeight": 4,
      "minHeight": 150,
      "minWidth": 450,
      "mobileBottomRow": 150,
      "mobileLeftColumn": 0,
      "mobileRightColumn": 587.25,
      "mobileTopRow": 0,
      "needsErrorInfo": false,
      "parentColumnSpace": 1,
      "parentId": "jd6m2w0g0x",
      "parentRowSpace": 1,
      "renderMode": "CANVAS",
      "responsiveBehavior": "fill",
      "rightColumn": 587.25,
      "shouldScrollContents": false,
      "tabId": "tab2",
      "tabName": "I5",
      "topRow": 0,
      "type": "CANVAS_WIDGET",
      "version": 1,
      "widgetId": "ko5h2d7j8q",
      "widgetName": "Canvas137"
    },
    {
      "borderRadius": "{{appsmith.theme.borderRadius.appBorderRadius}}",
      "bottomRow": 1010,
      "boxShadow": "{{appsmith.theme.boxShadow.appBoxShadow}}",
      "canExtend": false,
      "containerStyle": "none",
      "detachFromLayout": true,
      "dynamicBindingPathList": [
        {
          "key": "borderRadius"
        },
        {
          "key": "boxShadow"
        }
      ],
      "dynamicHeight": "AUTO_HEIGHT",
      "dynamicTriggerPathList": [],
      "flexLayers": [],
      "isLoading": false,
      "isVisible": true,
      "key": "d1i677ai0n",
      "leftColumn": 0,
      "maxDynamicHeight": 9000,
      "minDynamicHeight": 4,
      "minHeight": 190,
      "minWidth": 450,
      "mobileBottomRow": 191,
      "mobileLeftColumn": 0,
      "mobileRightColumn": 1566,
      "mobileTopRow": 1,
      "needsErrorInfo": false,
      "parentColumnSpace": 1,
      "parentId": "jd6m2w0g0x",
      "parentRowSpace": 1,
      "renderMode": "CANVAS",
      "responsiveBehavior": "fill",
      "rightColumn": 1566,
      "tabId": "tabal9gvdjrid",
      "tabName": "I7",
      "topRow": 1,
      "type": "CANVAS_WIDGET",
      "version": 1,
      "widgetId": "hq9pi3763l",
      "widgetName": "Canvas138"
    },
    {
      "borderRadius": "{{appsmith.theme.borderRadius.appBorderRadius}}",
      "bottomRow": 1010,
      "boxShadow": "{{appsmith.theme.boxShadow.appBoxShadow}}",
      "canExtend": false,
      "containerStyle": "none",
      "detachFromLayout": true,
      "dynamicBindingPathList": [
        {
          "key": "borderRadius"
        },
        {
          "key": "boxShadow"
        }
      ],
      "dynamicHeight": "AUTO_HEIGHT",
      "dynamicTriggerPathList": [],
      "flexLayers": [],
      "isLoading": false,
      "isVisible": true,
      "key": "d1i677ai0n",
      "leftColumn": 0,
      "maxDynamicHeight": 9000,
      "minDynamicHeight": 4,
      "minHeight": 190,
      "minWidth": 450,
      "mobileBottomRow": 191,
      "mobileLeftColumn": 0,
      "mobileRightColumn": 1566,
      "mobileTopRow": 1,
      "needsErrorInfo": false,
      "parentColumnSpace": 1,
      "parentId": "jd6m2w0g0x",
      "parentRowSpace": 1,
      "renderMode": "CANVAS",
      "responsiveBehavior": "fill",
      "rightColumn": 1566,
      "tabId": "tabzgxmsdmoru",
      "tabName": "I9",
      "topRow": 1,
      "type": "CANVAS_WIDGET",
      "version": 1,
      "widgetId": "6cbkfuvnh1",
      "widgetName": "Canvas139"
    }
  ],
  "defaultTab": "",
  "dynamicBindingPathList": [
    {
      "key": "borderRadius"
    },
    {
      "key": "boxShadow"
    }
  ],
  "dynamicHeight": "FIXED",
  "dynamicPropertyPathList": [],
  "dynamicTriggerPathList": [],
  "flexVerticalAlignment": "stretch",
  "isCanvas": true,
  "isLoading": false,
  "isVisible": true,
  "key": "73pct7ah8i",
  "leftColumn": 0,
  "maxDynamicHeight": 9000,
  "minDynamicHeight": 10,
  "minWidth": 450,
  "mobileBottomRow": 21,
  "mobileLeftColumn": 13,
  "mobileRightColumn": 37,
  "mobileTopRow": 6,
  "needsErrorInfo": false,
  "originalBottomRow": 109,
  "originalTopRow": 89,
  "parentColumnSpace": 24.46875,
  "parentId": "777i07m3pt",
  "parentRowSpace": 10,
  "renderMode": "CANVAS",
  "responsiveBehavior": "fill",
  "rightColumn": 64,
  "shouldScrollContents": true,
  "shouldShowTabs": true,
  "tabsObj": {
    "tab1": {
      "id": "tab1",
      "index": 0,
      "isVisible": true,
      "label": "I3",
      "positioning": "vertical",
      "widgetId": "lsw27ydv9u"
    },
    "tab2": {
      "id": "tab2",
      "index": 1,
      "isVisible": true,
      "label": "I5",
      "positioning": "vertical",
      "widgetId": "ko5h2d7j8q"
    },
    "tabal9gvdjrid": {
      "id": "tabal9gvdjrid",
      "index": 2,
      "isVisible": true,
      "label": "I7",
      "widgetId": "hq9pi3763l"
    },
    "tabzgxmsdmoru": {
      "id": "tabzgxmsdmoru",
      "index": 3,
      "isVisible": true,
      "label": "I9",
      "widgetId": "6cbkfuvnh1"
    }
  },
  "topRow": 4,
  "type": "TABS_WIDGET",
  "version": 3,
  "widgetId": "jd6m2w0g0x",
  "widgetName": "Tabs2"
}